cdk_minecraft/__init__.py
cdk_minecraft/backend_api.py
cdk_minecraft/constants.py
cdk_minecraft/construct_.py
cdk_minecraft/frontend.py
cdk_minecraft/stack.py
cdk_minecraft/deploy_server_batch_job/__init__.py
cdk_minecraft/deploy_server_batch_job/deprovision_state_machine.py
cdk_minecraft/deploy_server_batch_job/job_definition.py
cdk_minecraft/deploy_server_batch_job/job_queue.py
cdk_minecraft/deploy_server_batch_job/provision_state_machine.py
cdk_minecraft/deploy_server_batch_job/server_backup_docker_image.py
cdk_minecraft/deploy_server_batch_job/state_machine_input_validator/__init__.py
cdk_minecraft/deploy_server_batch_job/state_machine_input_validator/state_machine_input_validator_lambda.py
cdk_minecraft/deploy_server_batch_job/state_machine_input_validator/resources/index.py
cdk_minecraft/deploy_server_batch_job/state_machine_input_validator/resources/requirements.txt
cdk_minecraft/resources/__init__.py
cdk_minecraft/resources/awscdk-minecraft-server-deployer/.dockerignore
cdk_minecraft/resources/awscdk-minecraft-server-deployer/Dockerfile
cdk_minecraft/resources/awscdk-minecraft-server-deployer/README.md
cdk_minecraft/resources/awscdk-minecraft-server-deployer/app.py
cdk_minecraft/resources/awscdk-minecraft-server-deployer/pyproject.toml
cdk_minecraft/resources/awscdk-minecraft-server-deployer/setup.cfg
cdk_minecraft/resources/awscdk-minecraft-server-deployer/setup.py
cdk_minecraft/resources/awscdk-minecraft-server-deployer/resources/user-data.template.sh
cdk_minecraft/resources/awscdk-minecraft-server-deployer/src/minecraft_server_deployer/__init__.py
cdk_minecraft/resources/awscdk-minecraft-server-deployer/src/minecraft_server_deployer/server_stack.py
cdk_minecraft/resources/minecraft-platform-backend-api/README.md
cdk_minecraft/resources/minecraft-platform-backend-api/pyproject.toml
cdk_minecraft/resources/minecraft-platform-backend-api/setup.cfg
cdk_minecraft/resources/minecraft-platform-backend-api/setup.py
awscdk_minecraft-2.2.0.dist-info/METADATA
awscdk_minecraft-2.2.0.dist-info/WHEEL
awscdk_minecraft-2.2.0.dist-info/top_level.txt
awscdk_minecraft-2.2.0.dist-info/RECORD
