Metadata-Version: 2.1
Name: awscdk-minecraft
Version: 2.2.0
Summary: AWS CDK construct for hosting a Minecraft server Platform-as-a-Service.
Home-page: https://github.com/mlops-club/awscdk-minecraft
Author: The MLOps Club
Author-email: 
License: MPL 2.0
Project-URL: Documentation, https://github.com/mlops-club/awscdk-minecraft
Project-URL: Source, https://github.com/mlops-club/awscdk-minecraft
Keywords: Minecraft,AWS CDK
Classifier: Programming Language :: Python :: 3.7
Classifier: Programming Language :: Python :: 3.8
Classifier: Programming Language :: Python :: 3.9
Classifier: Programming Language :: Python :: 3.10
Requires-Python: >=3.7
Requires-Dist: aws-cdk-lib (<3.0.0,>=2.45.0)
Requires-Dist: constructs (<11.0.0,>=10.0.5)
Requires-Dist: aws-cdk.aws-batch-alpha (==2.40.0a0)
Requires-Dist: aws-cdk.aws-lambda-python-alpha
Requires-Dist: aws-prototyping-sdk.static-website
Requires-Dist: cdk-ecr-deployment (>=2.0.0)
Requires-Dist: importlib-metadata ; python_version < "3.8"
Provides-Extra: all
Requires-Dist: pytest ; extra == 'all'
Requires-Dist: pytest-cov ; extra == 'all'
Requires-Dist: pytest-xdist ; extra == 'all'
Requires-Dist: twine ; extra == 'all'
Provides-Extra: dev
Requires-Dist: pytest ; extra == 'dev'
Requires-Dist: pytest-cov ; extra == 'dev'
Requires-Dist: pytest-xdist ; extra == 'dev'
Provides-Extra: publish
Requires-Dist: twine ; extra == 'publish'
Provides-Extra: test
Requires-Dist: pytest ; extra == 'test'
Requires-Dist: pytest-cov ; extra == 'test'
Requires-Dist: pytest-xdist ; extra == 'test'
